trialist/__about__.py
trialist/__init__.py
trialist/experiment.py
trialist/trial_viewer.py
trialist-0.2.0.dist-info/METADATA
trialist-0.2.0.dist-info/WHEEL
trialist-0.2.0.dist-info/licenses/LICENSE
trialist-0.2.0.dist-info/RECORD
