Metadata-Version: 2.4
Name: trialist
Version: 0.2.0
Summary: Library for running experiments in Python. Supports logging, experimental loops with checkpointing.
Project-URL: Documentation, https://github.com/Yiannis128/trialist-python#readme
Project-URL: Issues, https://github.com/Yiannis128/trialist-python/issues
Project-URL: Source, https://github.com/Yiannis128/trialist-python
Author-email: Yiannis Charalambous <yiannis128@hotmail.com>
License-Expression: GPL-3.0
License-File: LICENSE
Classifier: Development Status :: 4 - Beta
Classifier: Programming Language :: Python
Classifier: Programming Language :: Python :: 3.12
Requires-Python: >=3.12
Requires-Dist: ipykernel
Requires-Dist: ipywidgets
Requires-Dist: joblib
Requires-Dist: loguru
